p2obt/__init__.py
p2obt/automate.py
p2obt/backend/__init__.py
p2obt/backend/compose.py
p2obt/backend/parse.py
p2obt/backend/query.py
p2obt/backend/upload.py
p2obt/backend/utils.py
p2obt/config/Extensive Target Information.xlsx
p2obt/config/__init__.py
p2obt/config/options.py
p2obt/config/templates.toml
p2obt-4.1.3.dist-info/licenses/LICENSE
p2obt-4.1.3.dist-info/METADATA
p2obt-4.1.3.dist-info/WHEEL
p2obt-4.1.3.dist-info/top_level.txt
p2obt-4.1.3.dist-info/RECORD
