Metadata-Version: 2.4
Name: p2obt
Version: 4.1.3
Summary: The Phase 2 OB tools (p2obt) automate the MATISSE observation preparation/upload.
Author-email: Marten Scheuck <martenscheuck@gmail.com>
License: MIT License
Project-URL: repository, https://github.com/MBSck/p2obt
Keywords: astronomy,observations,observation-preparation,VLT
Classifier: Development Status :: 5 - Production/Stable
Classifier: Framework :: Pytest
Classifier: Framework :: Sphinx
Classifier: License :: OSI Approved :: MIT License
Classifier: Natural Language :: English
Classifier: Operating System :: OS Independent
Classifier: Programming Language :: Python :: 3
Classifier: Programming Language :: Python :: 3.9
Classifier: Programming Language :: Python :: 3.10
Classifier: Programming Language :: Python :: 3.11
Classifier: Topic :: Scientific/Engineering :: Astronomy
Classifier: Topic :: Scientific/Engineering :: Physics
Requires-Python: >=3.10
License-File: LICENSE
Requires-Dist: astropy>=6.1.7
Requires-Dist: astroquery>=0.4.9.post1
Requires-Dist: attrs>=25.1.0
Requires-Dist: numpy>=2.2.2
Requires-Dist: openpyxl>=3.1.5
Requires-Dist: p2api>=1.0.10
Requires-Dist: pandas>=2.2.3
Requires-Dist: toml>=0.10.2
Dynamic: license-file
